starlette_api/__init__.py
starlette_api/applications.py
starlette_api/codecs/__init__.py
starlette_api/codecs/base.py
starlette_api/codecs/http/__init__.py
starlette_api/codecs/http/jsondata.py
starlette_api/codecs/http/multipart.py
starlette_api/codecs/http/urlencoded.py
starlette_api/codecs/websockets/__init__.py
starlette_api/codecs/websockets/bytes.py
starlette_api/codecs/websockets/json.py
starlette_api/codecs/websockets/text.py
starlette_api/components/__init__.py
starlette_api/components/asgi.py
starlette_api/components/base.py
starlette_api/components/validation.py
starlette_api/endpoints.py
starlette_api/exceptions.py
starlette_api/http.py
starlette_api/injection.py
starlette_api/negotiation.py
starlette_api/pagination/__init__.py
starlette_api/pagination/limit_offset.py
starlette_api/pagination/page_number.py
starlette_api/pagination/paginator.py
starlette_api/resources.py
starlette_api/responses.py
starlette_api/routing.py
starlette_api/schemas.py
starlette_api/templates/redoc.html
starlette_api/templates/swagger_ui.html
starlette_api/types.py
starlette_api/utils.py
starlette_api/validation.py
starlette_api/websockets.py
starlette_api-0.7.0.dist-info/LICENSE
starlette_api-0.7.0.dist-info/WHEEL
starlette_api-0.7.0.dist-info/METADATA
starlette_api-0.7.0.dist-info/RECORD
